heva/__init__.py
heva/cart_plot.py
heva/details.py
heva/dist.py
heva/gev.py
heva/gev_plot.py
heva/graphics.py
heva/helper.py
heva/io.py
heva/preprocess.py
test/__init__.py
test/test_helper.py
hevapy-0.0.2.dist-info/LICENSE
hevapy-0.0.2.dist-info/METADATA
hevapy-0.0.2.dist-info/WHEEL
hevapy-0.0.2.dist-info/top_level.txt
hevapy-0.0.2.dist-info/RECORD
